blockchainetl/__init__.py
blockchainetl/atomic_counter.py
blockchainetl/csv_utils.py
blockchainetl/exporters.py
blockchainetl/file_utils.py
blockchainetl/logging_utils.py
blockchainetl/jobs/__init__.py
blockchainetl/jobs/base_job.py
blockchainetl/jobs/exporters/__init__.py
blockchainetl/jobs/exporters/aws_kinesis_item_exporter.py
blockchainetl/jobs/exporters/buffered_item_exporter.py
blockchainetl/jobs/exporters/composite_item_exporter.py
blockchainetl/jobs/exporters/console_item_exporter.py
blockchainetl/jobs/exporters/gcs_item_exporter.py
blockchainetl/jobs/exporters/google_pubsub_item_exporter.py
blockchainetl/jobs/exporters/in_memory_item_exporter.py
blockchainetl/jobs/exporters/kafka_exporter.py
blockchainetl/jobs/exporters/multi_item_exporter.py
blockchainetl/jobs/exporters/multifile_item_exporter.py
blockchainetl/jobs/exporters/postgres_item_exporter.py
blockchainetl/jobs/exporters/singlefile_item_exporter.py
blockchainetl/jobs/exporters/converters/__init__.py
blockchainetl/jobs/exporters/converters/aws_kinesis_item_exporter.py
blockchainetl/jobs/exporters/converters/composite_item_converter.py
blockchainetl/jobs/exporters/converters/int_to_decimal_item_converter.py
blockchainetl/jobs/exporters/converters/int_to_string_item_converter.py
blockchainetl/jobs/exporters/converters/list_field_item_converter.py
blockchainetl/jobs/exporters/converters/simple_item_converter.py
blockchainetl/jobs/exporters/converters/unix_timestamp_item_converter.py
klaytnetl/__init__.py
klaytnetl/__main__.py
klaytnetl/atomic_counter.py
klaytnetl/csv_utils.py
klaytnetl/erc20_abi.py
klaytnetl/exporters.py
klaytnetl/json_rpc_requests.py
klaytnetl/misc_utils.py
klaytnetl/progress_logger.py
klaytnetl/thread_local_proxy.py
klaytnetl/trace_progress_logger.py
klaytnetl/utils.py
klaytnetl/web3_utils.py
klaytnetl/cli/__init__.py
klaytnetl/cli/export_all.py
klaytnetl/cli/export_block_group.py
klaytnetl/cli/export_blocks_and_transactions.py
klaytnetl/cli/export_contracts.py
klaytn_etl_test-0.1.11.dist-info/LICENSE
klaytn_etl_test-0.1.11.dist-info/METADATA
klaytn_etl_test-0.1.11.dist-info/WHEEL
klaytn_etl_test-0.1.11.dist-info/entry_points.txt
klaytn_etl_test-0.1.11.dist-info/top_level.txt
klaytn_etl_test-0.1.11.dist-info/RECORD
