Metadata-Version: 2.1
Name: klaytn-etl-test
Version: 0.1.11
Summary: Tools for exporting Klaytn blockchain data to JSON
Home-page: https://github.com/klaytn/klaytn-etl
Author: Yongchan Hong
Author-email: chan.hong@krustuniverse.com
Project-URL: Bug Reports, https://github.com/klaytn/klaytn-etl/issues
Project-URL: Source, https://github.com/klaytn/klaytn-etl/tree/klaytn-etl
Keywords: klaytn,etl,batch
Classifier: Development Status :: 4 - Beta
Classifier: Intended Audience :: Developers
Classifier: License :: OSI Approved :: MIT License
Classifier: Programming Language :: Python :: 3
Classifier: Programming Language :: Python :: 3.7
Classifier: Programming Language :: Python :: 3.8
Classifier: Programming Language :: Python :: 3.9
Requires-Python: >=3.7.2,<4
License-File: LICENSE
Requires-Dist: web3 (<6,>=5.29)
Requires-Dist: eth-rlp (<0.3)
Requires-Dist: eth-utils (==1.10)
Requires-Dist: eth-abi (==2.1.1)
Requires-Dist: python-dateutil (<3,>=2.8.0)
Requires-Dist: click (==8.0.4)
Requires-Dist: ethereum-dasm (==0.1.4)
Requires-Dist: pytz (==2022.1)
Requires-Dist: base58
Requires-Dist: requests
Requires-Dist: boto3
Requires-Dist: google-cloud-storage
Provides-Extra: dev
Requires-Dist: pytest (~=4.3.0) ; extra == 'dev'
